README
setup.py
WTAlchemy.egg-info/PKG-INFO
WTAlchemy.egg-info/SOURCES.txt
WTAlchemy.egg-info/dependency_links.txt
WTAlchemy.egg-info/not-zip-safe
WTAlchemy.egg-info/requires.txt
WTAlchemy.egg-info/top_level.txt
wtalchemy/__init__.py
wtalchemy/fields.py
wtalchemy/orm.py
wtalchemy/validators.py