Metadata-Version: 1.0
Name: WTAlchemy
Version: 0.1b2
Summary: WTForms SQAlchemy extension
Home-page: https://github.com/jean-philippe/WTAlchemy
Author: Jean-Philippe Serafin
Author-email: serafinjp@gmail.com
License: mit
Platform: any
Classifier: Development Status :: 4 - Beta
Classifier: Environment :: Web Environment
Classifier: Intended Audience :: Developers
Classifier: License :: OSI Approved :: MIT License
Classifier: Operating System :: OS Independent
Classifier: Programming Language :: Python
Classifier: Topic :: Internet :: WWW/HTTP :: Dynamic Content
Classifier: Topic :: Software Development :: Libraries :: Python Modules
